server.py
ado/__init__.py
ado/auth.py
ado/cache.py
ado/client.py
ado/config.py
ado/errors.py
ado/helpers.py
ado/lookups.py
ado/models.py
ado/py.typed
ado/resources.py
ado/retry.py
ado/telemetry.py
ado/tools.py
ado/enhanced_tools/__init__.py
ado/enhanced_tools/projects.py
ado/pipelines/__init__.py
ado/pipelines/builds.py
ado/pipelines/logs.py
ado/pipelines/pipelines.py
ado/processes/__init__.py
ado/processes/client.py
ado/processes/models.py
ado/processes/tools.py
ado/processes/utils.py
ado/utils/__init__.py
ado/utils/fuzzy_matching.py
ado/utils/token_estimation.py
ado/work_items/__init__.py
ado/work_items/batch_client.py
ado/work_items/batch_operations.py
ado/work_items/client.py
ado/work_items/comments_and_history.py
ado/work_items/comments_client.py
ado/work_items/crud_client.py
ado/work_items/crud_operations.py
ado/work_items/field_validators.py
ado/work_items/models.py
ado/work_items/path_validators.py
ado/work_items/query_client.py
ado/work_items/query_operations.py
ado/work_items/query_utils.py
ado/work_items/relationship_validators.py
ado/work_items/state_validators.py
ado/work_items/tools.py
ado/work_items/type_client.py
ado/work_items/type_introspection.py
ado/work_items/validation.py
ado_mcp-0.0.1.dist-info/licenses/LICENSE.md
ado_mcp-0.0.1.dist-info/METADATA
ado_mcp-0.0.1.dist-info/WHEEL
ado_mcp-0.0.1.dist-info/entry_points.txt
ado_mcp-0.0.1.dist-info/top_level.txt
ado_mcp-0.0.1.dist-info/RECORD
