Metadata-Version: 2.4
Name: ado-mcp
Version: 0.0.1
Summary: An MCP server for Azure DevOps pipelines.
Author-email: Russell Boley <countrypeaches@gmail.com>
License-Expression: MIT
Project-URL: Homepage, https://github.com/raboley/ado-mcp
Project-URL: Repository, https://github.com/raboley/ado-mcp
Project-URL: Issues, https://github.com/raboley/ado-mcp/issues
Project-URL: Documentation, https://ado-mcp.readthedocs.io/
Keywords: azure-devops,mcp,model-context-protocol,ci-cd,pipelines,automation,devops,azure,llm,ai-tools
Classifier: Development Status :: 4 - Beta
Classifier: Intended Audience :: Developers
Classifier: Topic :: Software Development :: Build Tools
Classifier: Topic :: Software Development :: Libraries :: Python Modules
Classifier: Programming Language :: Python :: 3
Classifier: Programming Language :: Python :: 3.12
Classifier: Programming Language :: Python :: 3.13
Classifier: Operating System :: OS Independent
Classifier: Environment :: Console
Classifier: Typing :: Typed
Requires-Python: >=3.12
License-File: LICENSE.md
Requires-Dist: fastmcp>=2.10.0
Requires-Dist: requests>=2.30.0
Requires-Dist: python-dotenv>=1.0.0
Requires-Dist: opentelemetry-api>=1.20.0
Requires-Dist: opentelemetry-sdk>=1.20.0
Requires-Dist: opentelemetry-instrumentation-requests>=0.41b0
Requires-Dist: opentelemetry-exporter-otlp-proto-http>=1.20.0
Requires-Dist: PyYAML>=6.0.0
Requires-Dist: python-levenshtein>=0.27.1
Provides-Extra: dev
Requires-Dist: pytest>=8.0.0; extra == "dev"
Requires-Dist: pytest-asyncio>=1.0.0; extra == "dev"
Requires-Dist: pytest-cov>=6.2.1; extra == "dev"
Requires-Dist: pytest-mock>=3.14.1; extra == "dev"
Requires-Dist: pytest-xdist>=3.6.0; extra == "dev"
Requires-Dist: pytest-timeout>=2.1.0; extra == "dev"
Requires-Dist: ruff>=0.1.0; extra == "dev"
Requires-Dist: mypy>=1.0.0; extra == "dev"
Requires-Dist: types-requests>=2.30.0; extra == "dev"
Requires-Dist: types-PyYAML>=6.0.0; extra == "dev"
Requires-Dist: opentelemetry-api>=1.20.0; extra == "dev"
Requires-Dist: opentelemetry-sdk>=1.20.0; extra == "dev"
Requires-Dist: opentelemetry-instrumentation-requests>=0.41b0; extra == "dev"
Provides-Extra: docs
Requires-Dist: sphinx>=7.0.0; extra == "docs"
Requires-Dist: sphinx-rtd-theme>=2.0.0; extra == "docs"
Requires-Dist: sphinx-autodoc-typehints>=1.25.0; extra == "docs"
Requires-Dist: myst-parser>=2.0.0; extra == "docs"
Requires-Dist: sphinx-autobuild>=2024.2.0; extra == "docs"
Requires-Dist: opentelemetry-api>=1.20.0; extra == "docs"
Requires-Dist: opentelemetry-sdk>=1.20.0; extra == "docs"
Requires-Dist: opentelemetry-instrumentation-requests>=0.41b0; extra == "docs"
Dynamic: license-file
